pygeostat/__init__.py
pygeostat/pygeostat_parameters.py
pygeostat/data/__init__.py
pygeostat/data/data.py
pygeostat/data/grid_definition.py
pygeostat/data/h5_io.py
pygeostat/data/h5_pytables.py
pygeostat/data/iotools.py
pygeostat/data/__pycache__/__init__.cpython-310.pyc
pygeostat/data/__pycache__/__init__.cpython-311.pyc
pygeostat/data/__pycache__/__init__.cpython-312.pyc
pygeostat/data/__pycache__/__init__.cpython-313.pyc
pygeostat/data/__pycache__/data.cpython-310.pyc
pygeostat/data/__pycache__/data.cpython-311.pyc
pygeostat/data/__pycache__/data.cpython-312.pyc
pygeostat/data/__pycache__/data.cpython-313.pyc
pygeostat/data/__pycache__/grid_definition.cpython-310.pyc
pygeostat/data/__pycache__/grid_definition.cpython-311.pyc
pygeostat/data/__pycache__/grid_definition.cpython-312.pyc
pygeostat/data/__pycache__/grid_definition.cpython-313.pyc
pygeostat/data/__pycache__/h5_io.cpython-310.pyc
pygeostat/data/__pycache__/h5_io.cpython-311.pyc
pygeostat/data/__pycache__/h5_io.cpython-312.pyc
pygeostat/data/__pycache__/h5_io.cpython-313.pyc
pygeostat/data/__pycache__/h5_pytables.cpython-310.pyc
pygeostat/data/__pycache__/iotools.cpython-310.pyc
pygeostat/data/__pycache__/iotools.cpython-311.pyc
pygeostat/data/__pycache__/iotools.cpython-312.pyc
pygeostat/data/__pycache__/iotools.cpython-313.pyc
pygeostat/data/example_data/3d_correlation.dat
pygeostat/data/example_data/3d_estimate.out
pygeostat/data/example_data/3d_grid.out
pygeostat/data/example_data/97data.dat
pygeostat/data/example_data/accuracy_plot.dat
pygeostat/data/example_data/cluster.dat
pygeostat/data/example_data/data.dat
pygeostat/data/example_data/gmm_fit.out
pygeostat/data/example_data/grid2d_surf.dat
pygeostat/data/example_data/griddef.txt
pygeostat/data/example_data/location_plot.dat
pygeostat/data/example_data/oilsands.dat
pygeostat/data/example_data/parta.dat
pygeostat/data/example_data/partb.dat
pygeostat/data/example_data/partc.dat
pygeostat/data/example_data/point2d_ind.dat
pygeostat-1.2.0.dist-info/licenses/LICENSE
pygeostat-1.2.0.dist-info/METADATA
pygeostat-1.2.0.dist-info/WHEEL
pygeostat-1.2.0.dist-info/top_level.txt
pygeostat-1.2.0.dist-info/RECORD
