Metadata-Version: 2.4
Name: pygeostat
Version: 1.2.0
Summary: Python interface for geostatistics
Author: Jared Deutsch, Matthew Deutsch, Ryan Martin, Warren Black, Tyler Acorn, Mostafa Hadavand, Ryan Barnett
Maintainer-email: "Ronny A. Hernandez Mora" <ronnyale@ualberta.ca>
License: MIT
Project-URL: Documentation, https://www.ccgalberta.com/pygeostat/welcome.html
Project-URL: Source, https://github.com/CcgAlberta/pygeostat
Project-URL: Issues, https://github.com/CcgAlberta/pygeostat/issues
Keywords: geostatistics
Classifier: Intended Audience :: Science/Research
Classifier: License :: OSI Approved :: MIT License
Classifier: Operating System :: Microsoft
Classifier: Programming Language :: Python :: 3
Classifier: Programming Language :: Python :: 3.10
Classifier: Programming Language :: Python :: 3.11
Classifier: Programming Language :: Python :: 3.12
Classifier: Programming Language :: Python :: 3.13
Requires-Python: >=3.10
License-File: LICENSE
Requires-Dist: h5py>=3.13.0
Requires-Dist: matplotlib>=3.10.0
Requires-Dist: numba>=0.61.0
Requires-Dist: numpy>=2.1.3
Requires-Dist: pandas>=2.2.3
Requires-Dist: pillow>=11.1.0
Requires-Dist: probscale>=0.2.5
Requires-Dist: pyperclip>=1.9.0
Requires-Dist: scikit-learn>=1.6.1
Requires-Dist: scipy>=1.15.2
Requires-Dist: statsmodels>=0.14.4
Requires-Dist: tqdm>=4.67.1
Provides-Extra: dev
Requires-Dist: black>=25.1.0; extra == "dev"
Requires-Dist: jupyter>=1.1.1; extra == "dev"
Requires-Dist: jupyter-client>=8.6.3; extra == "dev"
Requires-Dist: mypy>=1.15.0; extra == "dev"
Requires-Dist: myst-parser>=4.0.1; extra == "dev"
Requires-Dist: nbconvert>=7.16.6; extra == "dev"
Requires-Dist: nbformat>=5.10.4; extra == "dev"
Requires-Dist: pyevtk>=1.6.0; extra == "dev"
Requires-Dist: pytest>=8.3.4; extra == "dev"
Requires-Dist: pytest-cov>=6.0.0; extra == "dev"
Requires-Dist: ruff>=0.9.6; extra == "dev"
Requires-Dist: sphinx>=8.1.3; extra == "dev"
Requires-Dist: sphinx-rtd-theme>=3.0.2; extra == "dev"
Provides-Extra: docs
Requires-Dist: sphinx>=8.1.3; extra == "docs"
Requires-Dist: nbsphinx>=0.8.8; extra == "docs"
Requires-Dist: sphinx-rtd-theme>=3.0.2; extra == "docs"
Requires-Dist: matplotlib>=3.10.0; extra == "docs"
Requires-Dist: ipython>=8.0.0; extra == "docs"
Requires-Dist: myst-parser>=4.0.1; extra == "docs"
Requires-Dist: pydata-sphinx-theme>=0.15.0; extra == "docs"
Dynamic: license-file
